matrix_io_malos-0.4.1-py3.6-nspkg.pth
matrix_io/malos/__init__.py
matrix_io/malos/cli.py
matrix_io/malos/driver.py
matrix_io_malos-0.4.1.dist-info/LICENSE
matrix_io_malos-0.4.1.dist-info/METADATA
matrix_io_malos-0.4.1.dist-info/WHEEL
matrix_io_malos-0.4.1.dist-info/entry_points.txt
matrix_io_malos-0.4.1.dist-info/namespace_packages.txt
matrix_io_malos-0.4.1.dist-info/top_level.txt
matrix_io_malos-0.4.1.dist-info/RECORD
