Metadata-Version: 2.1
Name: matrix-io-malos
Version: 0.4.1
Summary: MATRIX Labs MALOS libraries
Home-page: https://github.com/matrix-io/malos-python
Author: MATRIX Labs Team
Author-email: devel@matrixlabs.ai
License: GPLv3
Platform: UNKNOWN
Classifier: Development Status :: 4 - Beta
Classifier: Intended Audience :: Developers
Classifier: License :: OSI Approved :: GNU General Public License v3 (GPLv3)
Classifier: Intended Audience :: Developers
Classifier: Topic :: Utilities
Classifier: Natural Language :: English
Classifier: Operating System :: OS Independent
Classifier: Programming Language :: Python :: 3.6
Classifier: Programming Language :: Python :: 3.7
Requires-Dist: docopt (==0.6.2)
Requires-Dist: matrix-io-proto (>=0.0.32)
Requires-Dist: pyzmq (>=18.0.1)
Provides-Extra: test
Requires-Dist: coverage ; extra == 'test'
Requires-Dist: pytest ; extra == 'test'
Requires-Dist: pytest-cov ; extra == 'test'
